{
  "name": "88mph aDAI Pool",
  "nftNamePrefix": "88mph aDAI Pool ",
  "nftSymbolPrefix": "88mph-aDAI-",
  "moneyMarket": "AaveMarket",
  "interestModel": "LinearInterestModel",
  "feeModel": "PercentageFeeModel",
  "MinDepositPeriod": 7776000,
  "MaxDepositPeriod": 94670856,
  "MinDepositAmount": 0,
  "MaxDepositAmount": 10000e18,
  "stablecoin": "0x6B175474E89094C44Da98b954EedeAC495271d0F",
  "PoolMintingMultiplier": 1e18,
  "PoolDepositorRewardMultiplier": 0.1e18,
  "PoolFunderRewardMultiplier": 0.1e18,
  "IRMultiplier": 0.75e18
}